pngrenderer/__init__.py
pngrenderer/context.py
pngrenderer/core.py
pngrenderer-0.1.2.dist-info/DESCRIPTION.rst
pngrenderer-0.1.2.dist-info/METADATA
pngrenderer-0.1.2.dist-info/pydist.json
pngrenderer-0.1.2.dist-info/RECORD
pngrenderer-0.1.2.dist-info/top_level.txt
pngrenderer-0.1.2.dist-info/WHEEL
