Metadata-Version: 2.0
Name: pngrenderer
Version: 0.1.2
Summary: Render matplotlib png images to a zip file
Home-page: https://github.com/mindriot101/matplotlib-pngrenderer
Author: Simon Walker
Author-email: s.r.walker101@gmail.com
License: The MIT License (MIT)
Requires-Dist: matplotlib
